{"mockup":{"controls":{"control":[{"ID":"0","h":"448","measuredH":"400","measuredW":"450","properties":{"text":"Eureka. Be a part of Living History!"},"typeID":"BrowserWindow","w":"705","x":"72","y":"31","zOrder":"0"},{"ID":"1","h":"285","measuredH":"100","measuredW":"10","typeID":"VRule","x":"427","y":"154","zOrder":"1"},{"ID":"2","measuredH":"32","measuredW":"217","properties":{"size":"24","text":"Welcome to Eureka!"},"typeID":"Label","x":"97","y":"148","zOrder":"2"},{"ID":"3","measuredH":"80","measuredW":"275","typeID":"BlockOfText","x":"96","y":"190","zOrder":"3"},{"ID":"4","measuredH":"80","measuredW":"275","typeID":"BlockOfText","x":"97","y":"270","zOrder":"4"},{"ID":"5","measuredH":"21","measuredW":"111","properties":{"text":"Create an Account"},"typeID":"Label","x":"557","y":"154","zOrder":"5"},{"ID":"6","measuredH":"27","measuredW":"46","properties":{"text":"Email"},"typeID":"TextInput","w":"241","x":"492","y":"183","zOrder":"6"},{"ID":"7","h":"35","measuredH":"80","measuredW":"275","properties":{"text":"By clicking Sign up, I agree to the Terms of Service and Privacy Policy.\n"},"typeID":"Paragraph","w":"275","x":"472","y":"316","zOrder":"7"},{"ID":"8","measuredH":"27","measuredW":"70","properties":{"text":"Password"},"typeID":"TextInput","w":"241","x":"492","y":"247","zOrder":"8"},{"ID":"9","measuredH":"27","measuredW":"121","properties":{"text":"Re-type Password"},"typeID":"TextInput","w":"241","x":"492","y":"280","zOrder":"9"},{"ID":"10","measuredH":"27","measuredW":"76","properties":{"text":"Username"},"typeID":"TextInput","w":"241","x":"492","y":"214","zOrder":"10"},{"ID":"11","measuredH":"27","measuredW":"70","properties":{"text":"Sign up"},"typeID":"Button","x":"569","y":"358","zOrder":"11"},{"ID":"12","h":"21","measuredH":"80","measuredW":"275","properties":{"text":"Already have an account?","underline":"false"},"typeID":"Paragraph","w":"156","x":"492","y":"412","zOrder":"12"},{"ID":"13","h":"21","measuredH":"80","measuredW":"275","properties":{"text":"Click Here","underline":"true"},"typeID":"Paragraph","w":"69","x":"648","y":"412","zOrder":"13"},{"ID":"15","h":"38","measuredH":"70","measuredW":"100","typeID":"Canvas","w":"705","x":"71","y":"100","zOrder":"14"},{"ID":"16","measuredH":"32","measuredW":"82","properties":{"size":"24","text":"Eureka!"},"typeID":"Label","x":"391","y":"104","zOrder":"15"}]},"measuredH":"479","measuredW":"777","mockupH":"448","mockupW":"706","version":"1.0"}}
